exospherehost/__init__.py
exospherehost/_version.py
exospherehost/models.py
exospherehost/runtime.py
exospherehost/signals.py
exospherehost/statemanager.py
exospherehost/node/BaseNode.py
exospherehost/node/__init__.py
exospherehost-0.0.2.dist-info/METADATA
exospherehost-0.0.2.dist-info/WHEEL
exospherehost-0.0.2.dist-info/top_level.txt
exospherehost-0.0.2.dist-info/RECORD
