Metadata-Version: 2.4
Name: exospherehost
Version: 0.0.2
Summary: Official Python SDK for ExosphereHost
Author-email: ExosphereHost <nivedit@exosphere.host>
Project-URL: Homepage, https://exosphere.host
Project-URL: Documentation, https://docs.exosphere.host
Project-URL: Repository, https://github.com/exospherehost/exospherehost/tree/main/python-sdk
Classifier: Development Status :: 4 - Beta
Classifier: Intended Audience :: Developers
Classifier: License :: OSI Approved :: MIT License
Classifier: Operating System :: OS Independent
Classifier: Programming Language :: Python :: 3
Classifier: Programming Language :: Python :: 3.12
Classifier: Programming Language :: Python :: 3.13
Classifier: Topic :: Software Development :: Libraries :: Python Modules
Requires-Python: >=3.12
Requires-Dist: aiohttp>=3.12.15
Requires-Dist: pydantic>=2.11.7
